{"cameraMode":{"drawMode":0,"name":"Shaded","section":"Shading Mode"},"sceneLighting":true,"audioPlay":false,"sceneViewState":{"m_AlwaysRefresh":false,"showFog":true,"showSkybox":true,"showFlares":true,"showImageEffects":true,"showParticleSystems":true,"showVisualEffectGraphs":true,"m_FxEnabled":true},"in2DMode":false,"pivot":{"x":267.81109619140627,"y":8.017446517944336,"z":368.6851806640625},"rotation":{"x":-0.041252609342336658,"y":-0.6439087986946106,"z":0.03480483219027519,"w":-0.7631976008415222},"size":12.12435531616211,"orthographic":false}